MANIFEST.in
requirements.txt
setup.py
test_requirements.txt
third_party_requirements.txt
version.txt
cloudshell/__init__.py
cloudshell/networking/__init__.py
cloudshell/networking/ericsson/__init__.py
cloudshell/networking/ericsson/ericsson_configuration_operations.py
cloudshell/networking/ericsson/ericsson_connectivity_operations.py
cloudshell/networking/ericsson/ericsson_firmware_operations.py
cloudshell/networking/ericsson/ericsson_run_command_operations.py
cloudshell/networking/ericsson/ericsson_state_operations.py
cloudshell/networking/ericsson/autoload/__init__.py
cloudshell/networking/ericsson/autoload/ericsson_generic_snmp_autoload.py
cloudshell/tests/__init__.py
cloudshell/tests/cloudshell_networking_ericsson_tests.py
cloudshell/tests/networking/__init__.py
cloudshell/tests/networking/ericsson/__init__.py
cloudshell/tests/networking/ericsson/configuration/__init__.py
cloudshell/tests/networking/ericsson/configuration/tests_ericsson_configuration.py
cloudshell/tests/networking/ericsson/connectivity/__init__.py
cloudshell/tests/networking/ericsson/connectivity/tests_ericsson_connectivity.py
cloudshell/tests/networking/ericsson/firmware/__init__.py
cloudshell/tests/networking/ericsson/firmware/tests_ericsson_firmware_ops.py
cloudshell/tests/networking/ericsson/state/__init__.py
cloudshell/tests/networking/ericsson/state/test_ericsson_state_operations.py
cloudshell_networking_ericsson.egg-info/PKG-INFO
cloudshell_networking_ericsson.egg-info/SOURCES.txt
cloudshell_networking_ericsson.egg-info/dependency_links.txt
cloudshell_networking_ericsson.egg-info/requires.txt
cloudshell_networking_ericsson.egg-info/top_level.txt