Metadata-Version: 1.0
Name: cloudshell-networking-ericsson
Version: 1.0.16
Summary: QualiSystems networking ericsson specific package
Home-page: http://www.qualisystems.com/
Author: QualiSystems
Author-email: info@qualisystems.com
License: UNKNOWN
Platform: UNKNOWN
